{"data":{"allMarkdownRemark":{"edges":[{"node":{"fields":{"slug":"/about"},"id":"53d32a18-d72b-544b-b64f-54f0a39cb162","frontmatter":{"title":"David Jaimes","parents":["About"]}}},{"node":{"fields":{"slug":"/astro/eclipsing-binaries"},"id":"6fc72b80-db4f-5bfd-b7c2-25c3a18641c7","frontmatter":{"title":"Eclipsing Binaries","parents":["Astronomy"]}}},{"node":{"fields":{"slug":"/astro/jskycalc"},"id":"4e65504e-173c-556a-9b4b-a2cc7dce50b9","frontmatter":{"title":"JSkyCalc","parents":["Astronomy"]}}},{"node":{"fields":{"slug":"/blog/first-blog"},"id":"8749280a-f3f9-5ac5-bae7-f9d808ce078c","frontmatter":{"title":"First Blog","parents":["Blog"]}}},{"node":{"fields":{"slug":"/blog/second-blog"},"id":"7d0584fc-9089-5a53-ba07-f6dab1fa1644","frontmatter":{"title":"Second Blog","parents":["Blog"]}}},{"node":{"fields":{"slug":"/docs/linear-regression"},"id":"532bc50f-0f56-5801-a889-e5f02e0b34f3","frontmatter":{"title":"Linear Regression","parents":["Docs"]}}},{"node":{"fields":{"slug":"/legal/terms"},"id":"83b61e61-4adb-56e7-a26f-2c290feb5cea","frontmatter":{"title":"Terms of Use","parents":["Legal"]}}},{"node":{"fields":{"slug":"/macOS/setup"},"id":"0bb1006a-4c5d-5a91-ba68-4395274a2dbb","frontmatter":{"title":"Setup","parents":["macOS"]}}}]}}}